{"cameraMode":{"drawMode":0,"name":"Shaded","section":"Shading Mode"},"sceneLighting":true,"audioPlay":false,"sceneViewState":{"m_AlwaysRefresh":false,"showFog":true,"showSkybox":true,"showFlares":true,"showImageEffects":true,"showParticleSystems":true,"showVisualEffectGraphs":true,"m_FxEnabled":true},"in2DMode":false,"pivot":{"x":18.33022117614746,"y":-5.2838897705078129,"z":-13.629812240600586},"rotation":{"x":-0.07013679295778275,"y":0.9278420209884644,"z":-0.28885576128959658,"w":-0.22528797388076783},"size":29.721498489379884,"orthographic":false}